AUTHORS.rst
CONTRIBUTING.rst
HISTORY.rst
LICENSE
MANIFEST.in
README.rst
setup.cfg
setup.py
docs/Makefile
docs/authors.rst
docs/conf.py
docs/contributing.rst
docs/history.rst
docs/index.rst
docs/installation.rst
docs/make.bat
docs/readme.rst
docs/usage.rst
tests/__init__.py
tests/test_turnmp4.py
turnmp4/__init__.py
turnmp4/cli.py
turnmp4/turnmp4.py
turnmp4.egg-info/PKG-INFO
turnmp4.egg-info/SOURCES.txt
turnmp4.egg-info/dependency_links.txt
turnmp4.egg-info/entry_points.txt
turnmp4.egg-info/not-zip-safe
turnmp4.egg-info/requires.txt
turnmp4.egg-info/top_level.txt